martian/__init__.py
martian/main.py
martian/markdown/__init__.py
martian/markdown/ast.py
martian/markdown/types.py
martian/notion/__init__.py
martian/notion/blocks.py
martian/notion/common.py
martian/notion/language_map.json
martian/notion/utils.py
martian/parser/__init__.py
martian/parser/internal.py
pymartian-1.0.0.dist-info/licenses/LICENSE
pymartian-1.0.0.dist-info/METADATA
pymartian-1.0.0.dist-info/WHEEL
pymartian-1.0.0.dist-info/top_level.txt
pymartian-1.0.0.dist-info/RECORD
