Metadata-Version: 2.4
Name: pymartian
Version: 1.0.0
Summary: Convert Markdown to Notion API Blocks and RichText
Author: Martian Python Port
Author-email: Your Name <your.email@example.com>
Maintainer-email: Your Name <your.email@example.com>
License: MIT
Project-URL: Homepage, https://github.com/xwEric/pymartian
Project-URL: Documentation, https://github.com/xwEric/pymartian#readme
Project-URL: Repository, https://github.com/xwEric/pymartian.git
Project-URL: Issues, https://github.com/xwEric/pymartian/issues
Keywords: markdown,notion,converter,gfm,github-flavored-markdown
Classifier: Development Status :: 4 - Beta
Classifier: Intended Audience :: Developers
Classifier: License :: OSI Approved :: MIT License
Classifier: Programming Language :: Python :: 3
Classifier: Programming Language :: Python :: 3.10
Classifier: Programming Language :: Python :: 3.11
Classifier: Programming Language :: Python :: 3.12
Classifier: Topic :: Software Development :: Libraries :: Python Modules
Classifier: Topic :: Text Processing :: Markup :: Markdown
Requires-Python: >=3.10
License-File: LICENSE
Requires-Dist: markdown-it-py>=3.0.0
Requires-Dist: mdit-py-plugins>=0.4.0
Provides-Extra: dev
Requires-Dist: pytest>=7.4.0; extra == "dev"
Requires-Dist: pytest-cov>=4.1.0; extra == "dev"
Requires-Dist: black>=23.0.0; extra == "dev"
Requires-Dist: isort>=5.12.0; extra == "dev"
Requires-Dist: flake8>=6.0.0; extra == "dev"
Requires-Dist: mypy>=1.0.0; extra == "dev"
Dynamic: author
Dynamic: license-file
Dynamic: requires-python
